lektor_polymorphic_type.py
lektor_polymorphic_type-0.1.dist-info/LICENSE
lektor_polymorphic_type-0.1.dist-info/METADATA
lektor_polymorphic_type-0.1.dist-info/WHEEL
lektor_polymorphic_type-0.1.dist-info/entry_points.txt
lektor_polymorphic_type-0.1.dist-info/top_level.txt
lektor_polymorphic_type-0.1.dist-info/RECORD
