Metadata-Version: 2.1
Name: lektor-polymorphic-type
Version: 0.1
Summary: Add polymorphic field type to Lektor
Home-page: https://github.com/dairiki/lektor-polymorphic-type
Author: Jeff Dairiki
Author-email: dairiki@dairiki.org
License: MIT
Keywords: Lektor plugin
Platform: UNKNOWN
Classifier: Development Status :: 5 - Production/Stable
Classifier: Environment :: Plugins
Classifier: Environment :: Web Environment
Classifier: Framework :: Lektor
Classifier: Intended Audience :: Developers
Classifier: License :: OSI Approved :: MIT License
Classifier: Programming Language :: Python :: 2
Classifier: Programming Language :: Python :: 2.7
Classifier: Programming Language :: Python :: 3
Classifier: Programming Language :: Python :: 3.6
Classifier: Programming Language :: Python :: 3.7
Classifier: Programming Language :: Python :: 3.8
Classifier: Programming Language :: Python :: 3.9
